{"display_id": "0xJy2QVJTx8", "upload_date": "20140320", "description": "Specs & Prices: https://teksyndicate.com/videos/build-editinggamingcapture-pc-meet-ocelot\nMusic: http://bit.ly/Trk2ik, Merch: http://epicpants.com\nGame Deals: https://teksyndicate.com/gamedeals\n\nJoin the community: https://teksyndicate.com/user/register\nYou can create a new account or join using your google, steam, facebook, openID, twitter, linkedin, yahoo, etc.\n\nIf you have questions, comments, suggestions, or if would like to use a portion of this video please email us: inbox@teksyndicate.com\n\nFor marketing (sponsorship opportunities) inquiries email info@teksyndicate.com\n\nSocial:\nTwitter: https://twitter.com/teksyndicate\nLogan's Twitter: https://twitter.com/Logan_RTW\nFacebook: https://www.facebook.com/teksyndicate", "uploader_id": "razethew0rld", "extractor": "youtube", "height": 720, "_filename": "Build an Editing_Gaming_Capture PC - Meet The Ocelot-0xJy2QVJTx8.mp4", "like_count": 1567, "uploader": "Tek Syndicate", "duration": 813, "format_id": "22", "player_url": null, "id": "0xJy2QVJTx8", "subtitles": null, "stitle": "Build an Editing/Gaming/Capture PC: Meet The Ocelot", "view_count": 19059, "playlist": null, "title": "Build an Editing/Gaming/Capture PC: Meet The Ocelot", "url": "https://r14---sn-4g57kn6r.googlevideo.com/videoplayback?itag=22&mt=1395407808&upn=MxVzxKsbd3U&id=o-ALe2D0epTKGnwRqasgNf3CLxJbn33_ML0va0EAMhxV3S&mv=u&source=youtube&sver=3&expire=1395432694&key=yt5&ip=217.159.229.217&requiressl=yes&fexp=933513%2C912307%2C936906%2C929202%2C916612%2C906010%2C933611%2C937417%2C913434%2C936910%2C936913%2C934022&mws=yes&ms=au&sparams=id%2Cip%2Cipbits%2Citag%2Cratebypass%2Crequiressl%2Csource%2Cupn%2Cexpire&signature=9058F3204B221AB0EAEC84231EFA385534216639.9E0959AC2931BD16BB898DF5DA40D32609390080&ratebypass=yes&ipbits=0", "extractor_key": "Youtube", "format": "22 - 1280x720", "playlist_index": null, "dislike_count": 15, "width": 1280, "ext": "mp4", "annotations": null, "webpage_url": "https://www.youtube.com/watch?v=0xJy2QVJTx8", "formats": [
{"format": "171 - audio only (DASH webm audio)", "url": "https://r14---sn-4g57kn6r.googlevideo.com/videoplayback?itag=171&mt=1395407808&upn=kqCHO7cCi_0&ms=au&id=o-ALe2D0epTKGnwRqasgNf3CLxJbn33_ML0va0EAMhxV3S&lmt=1395378133817517&mv=u&source=youtube&sver=3&expire=1395432694&dur=812.651&key=yt5&ip=217.159.229.217&requiressl=yes&clen=12009026&fexp=933513%2C912307%2C936906%2C929202%2C916612%2C906010%2C933611%2C937417%2C913434%2C936910%2C936913%2C934022&mws=yes&gir=yes&sparams=clen%2Cdur%2Cgir%2Cid%2Cip%2Cipbits%2Citag%2Clmt%2Crequiressl%2Csource%2Cupn%2Cexpire&signature=3E1950F7B23B55195BA2D2B341B46EF7C75B8F3D.2C2C9CC25B680BA0CE6166A1F9F1B9C460595E6F&ipbits=0&ratebypass=yes", "vcodec": "none", "format_note": "DASH webm audio", "abr": 48, "player_url": null, "ext": "webm", "preference": -50, "format_id": "171"}, 
{"format": "140 - audio only (DASH audio)", "url": "https://r14---sn-4g57kn6r.googlevideo.com/videoplayback?itag=140&mt=1395407808&upn=kqCHO7cCi_0&ms=au&id=o-ALe2D0epTKGnwRqasgNf3CLxJbn33_ML0va0EAMhxV3S&lmt=1395359650845689&mv=u&source=youtube&sver=3&expire=1395432694&dur=812.698&key=yt5&ip=217.159.229.217&requiressl=yes&clen=12908264&fexp=933513%2C912307%2C936906%2C929202%2C916612%2C906010%2C933611%2C937417%2C913434%2C936910%2C936913%2C934022&mws=yes&gir=yes&sparams=clen%2Cdur%2Cgir%2Cid%2Cip%2Cipbits%2Citag%2Clmt%2Crequiressl%2Csource%2Cupn%2Cexpire&signature=F19463FAFF836A93A38554786119DC7B88CAAAE7.D94AE69DA4C2427D29C68C9BB90481E3507C1849&ipbits=0&ratebypass=yes", "vcodec": "none", "format_note": "DASH audio", "abr": 128, "player_url": null, "ext": "m4a", "preference": -50, "format_id": "140"}, 
{"format": "160 - 192p (DASH video)", "url": "https://r14---sn-4g57kn6r.googlevideo.com/videoplayback?itag=160&mt=1395407808&upn=kqCHO7cCi_0&ms=au&id=o-ALe2D0epTKGnwRqasgNf3CLxJbn33_ML0va0EAMhxV3S&lmt=1395359645470119&mv=u&source=youtube&sver=3&expire=1395432694&dur=812.644&key=yt5&ip=217.159.229.217&requiressl=yes&clen=11413071&fexp=933513%2C912307%2C936906%2C929202%2C916612%2C906010%2C933611%2C937417%2C913434%2C936910%2C936913%2C934022&mws=yes&gir=yes&sparams=clen%2Cdur%2Cgir%2Cid%2Cip%2Cipbits%2Citag%2Clmt%2Crequiressl%2Csource%2Cupn%2Cexpire&signature=696A1FF9D55DFDED57FF1327A20BCAD08343BA7B.A0A2A752B841E488A2B6F917042DE4AE299BA0F2&ipbits=0&ratebypass=yes", "format_note": "DASH video", "player_url": null, "ext": "mp4", "preference": -40, "format_id": "160", "height": 192, "resolution": "192p", "acodec": "none"}, 
{"format": "133 - 240p (DASH video)", "url": "https://r14---sn-4g57kn6r.googlevideo.com/videoplayback?itag=133&mt=1395407808&upn=kqCHO7cCi_0&ms=au&id=o-ALe2D0epTKGnwRqasgNf3CLxJbn33_ML0va0EAMhxV3S&lmt=1395359734105407&mv=u&source=youtube&sver=3&expire=1395432694&dur=812.644&key=yt5&ip=217.159.229.217&requiressl=yes&clen=24842845&fexp=933513%2C912307%2C936906%2C929202%2C916612%2C906010%2C933611%2C937417%2C913434%2C936910%2C936913%2C934022&mws=yes&gir=yes&sparams=clen%2Cdur%2Cgir%2Cid%2Cip%2Cipbits%2Citag%2Clmt%2Crequiressl%2Csource%2Cupn%2Cexpire&signature=A814B0F6E25827CD20AD337EF8C4749B524A409E.4EA9053F5BEE5C73E0D8DFE2A176750F673697B1&ipbits=0&ratebypass=yes", "format_note": "DASH video", "player_url": null, "ext": "mp4", "preference": -40, "format_id": "133", "height": 240, "resolution": "240p", "acodec": "none"}, 
{"format": "134 - 360p (DASH video)", "url": "https://r14---sn-4g57kn6r.googlevideo.com/videoplayback?itag=134&mt=1395407808&upn=kqCHO7cCi_0&ms=au&id=o-ALe2D0epTKGnwRqasgNf3CLxJbn33_ML0va0EAMhxV3S&lmt=1395359668402035&mv=u&source=youtube&sver=3&expire=1395432694&dur=812.644&key=yt5&ip=217.159.229.217&requiressl=yes&clen=33265482&fexp=933513%2C912307%2C936906%2C929202%2C916612%2C906010%2C933611%2C937417%2C913434%2C936910%2C936913%2C934022&mws=yes&gir=yes&sparams=clen%2Cdur%2Cgir%2Cid%2Cip%2Cipbits%2Citag%2Clmt%2Crequiressl%2Csource%2Cupn%2Cexpire&signature=1D83010FFC8D52242A251EEA6FCD934A843C2B1E.CADD163976C3E94E79ECE118B3AE3CBB18ECC0B5&ipbits=0&ratebypass=yes", "format_note": "DASH video", "player_url": null, "ext": "mp4", "preference": -40, "format_id": "134", "height": 360, "resolution": "360p", "acodec": "none"}, 
{"format": "135 - 480p (DASH video)", "url": "https://r14---sn-4g57kn6r.googlevideo.com/videoplayback?itag=135&mt=1395407808&upn=kqCHO7cCi_0&ms=au&id=o-ALe2D0epTKGnwRqasgNf3CLxJbn33_ML0va0EAMhxV3S&lmt=1395359650322012&mv=u&source=youtube&sver=3&expire=1395432694&dur=812.644&key=yt5&ip=217.159.229.217&requiressl=yes&clen=69662857&fexp=933513%2C912307%2C936906%2C929202%2C916612%2C906010%2C933611%2C937417%2C913434%2C936910%2C936913%2C934022&mws=yes&gir=yes&sparams=clen%2Cdur%2Cgir%2Cid%2Cip%2Cipbits%2Citag%2Clmt%2Crequiressl%2Csource%2Cupn%2Cexpire&signature=6AC8AD777E3C27FB27E8E0833757300525E19B65.5AEB22EB7C95F6408A7E0917A473EF147F707836&ipbits=0&ratebypass=yes", "format_note": "DASH video", "player_url": null, "ext": "mp4", "preference": -40, "format_id": "135", "height": 480, "resolution": "480p", "acodec": "none"}, 
{"format": "136 - 720p (DASH video)", "url": "https://r14---sn-4g57kn6r.googlevideo.com/videoplayback?itag=136&mt=1395407808&upn=kqCHO7cCi_0&ms=au&id=o-ALe2D0epTKGnwRqasgNf3CLxJbn33_ML0va0EAMhxV3S&lmt=1395359652591827&mv=u&source=youtube&sver=3&expire=1395432694&dur=812.644&key=yt5&ip=217.159.229.217&requiressl=yes&clen=140701589&fexp=933513%2C912307%2C936906%2C929202%2C916612%2C906010%2C933611%2C937417%2C913434%2C936910%2C936913%2C934022&mws=yes&gir=yes&sparams=clen%2Cdur%2Cgir%2Cid%2Cip%2Cipbits%2Citag%2Clmt%2Crequiressl%2Csource%2Cupn%2Cexpire&signature=2AD4E0360249A7BDBC0EB7502D5CE0BE0A4D35A9.6BE7DDFED5D3348833BF52576BFBB55FA92C38E6&ipbits=0&ratebypass=yes", "format_note": "DASH video", "player_url": null, "ext": "mp4", "preference": -40, "format_id": "136", "height": 720, "resolution": "720p", "acodec": "none"}, 
{"format": "137 - 1080p (DASH video)", "url": "https://r14---sn-4g57kn6r.googlevideo.com/videoplayback?itag=137&mt=1395407808&upn=kqCHO7cCi_0&ms=au&id=o-ALe2D0epTKGnwRqasgNf3CLxJbn33_ML0va0EAMhxV3S&lmt=1395359668161062&mv=u&source=youtube&sver=3&expire=1395432694&dur=812.644&key=yt5&ip=217.159.229.217&requiressl=yes&clen=272596101&fexp=933513%2C912307%2C936906%2C929202%2C916612%2C906010%2C933611%2C937417%2C913434%2C936910%2C936913%2C934022&mws=yes&gir=yes&sparams=clen%2Cdur%2Cgir%2Cid%2Cip%2Cipbits%2Citag%2Clmt%2Crequiressl%2Csource%2Cupn%2Cexpire&signature=E4E75BA756E3440B2AA9215695ADA6563B1046B1.36C05F617FC38DC26D6F7BFFC92AE7412324B7BC&ipbits=0&ratebypass=yes", "format_note": "DASH video", "player_url": null, "ext": "mp4", "preference": -40, "format_id": "137", "height": 1080, "resolution": "1080p", "acodec": "none"}, 
{"width": 176, "ext": "3gp", "format": "17 - 176x144", "url": "https://r14---sn-4g57kn6r.googlevideo.com/videoplayback?itag=17&mt=1395407808&upn=MxVzxKsbd3U&id=o-ALe2D0epTKGnwRqasgNf3CLxJbn33_ML0va0EAMhxV3S&mv=u&source=youtube&sver=3&expire=1395432694&key=yt5&ip=217.159.229.217&requiressl=yes&fexp=933513%2C912307%2C936906%2C929202%2C916612%2C906010%2C933611%2C937417%2C913434%2C936910%2C936913%2C934022&mws=yes&ms=au&sparams=id%2Cip%2Cipbits%2Citag%2Crequiressl%2Csource%2Cupn%2Cexpire&signature=A03B6A6EA09C59EEF5C572869002AA090392A8DD.66B4E3166DA8E3D9E2058EB02C0893312252EA57&ipbits=0&ratebypass=yes", "format_id": "17", "height": 144, "player_url": null}, 
{"width": 320, "ext": "3gp", "format": "36 - 320x240", "url": "https://r14---sn-4g57kn6r.googlevideo.com/videoplayback?itag=36&mt=1395407808&upn=MxVzxKsbd3U&id=o-ALe2D0epTKGnwRqasgNf3CLxJbn33_ML0va0EAMhxV3S&mv=u&source=youtube&sver=3&expire=1395432694&key=yt5&ip=217.159.229.217&requiressl=yes&fexp=933513%2C912307%2C936906%2C929202%2C916612%2C906010%2C933611%2C937417%2C913434%2C936910%2C936913%2C934022&mws=yes&ms=au&sparams=id%2Cip%2Cipbits%2Citag%2Crequiressl%2Csource%2Cupn%2Cexpire&signature=993DB86250D4B2C555FC8DDC2C2A9706DB0E1698.908D8DC09D7B9728FB7AB604ECFEF023D54689CC&ipbits=0&ratebypass=yes", "format_id": "36", "height": 240, "player_url": null}, 
{"width": 400, "ext": "flv", "format": "5 - 400x240", "url": "https://r14---sn-4g57kn6r.googlevideo.com/videoplayback?itag=5&mt=1395407808&upn=MxVzxKsbd3U&id=o-ALe2D0epTKGnwRqasgNf3CLxJbn33_ML0va0EAMhxV3S&mv=u&source=youtube&sver=3&expire=1395432694&key=yt5&ip=217.159.229.217&requiressl=yes&fexp=933513%2C912307%2C936906%2C929202%2C916612%2C906010%2C933611%2C937417%2C913434%2C936910%2C936913%2C934022&mws=yes&ms=au&sparams=id%2Cip%2Cipbits%2Citag%2Crequiressl%2Csource%2Cupn%2Cexpire&signature=2DE4CF1974E7ED09390B67009F70108498837B19.467A557B0E8F7BBD6425593483B3E7FD3BD2C00F&ipbits=0&ratebypass=yes", "format_id": "5", "height": 240, "player_url": null}, 
{"width": 640, "ext": "webm", "format": "43 - 640x360", "url": "https://r14---sn-4g57kn6r.googlevideo.com/videoplayback?itag=43&mt=1395407808&upn=MxVzxKsbd3U&id=o-ALe2D0epTKGnwRqasgNf3CLxJbn33_ML0va0EAMhxV3S&mv=u&source=youtube&sver=3&expire=1395432694&key=yt5&ip=217.159.229.217&requiressl=yes&fexp=933513%2C912307%2C936906%2C929202%2C916612%2C906010%2C933611%2C937417%2C913434%2C936910%2C936913%2C934022&mws=yes&ms=au&sparams=id%2Cip%2Cipbits%2Citag%2Cratebypass%2Crequiressl%2Csource%2Cupn%2Cexpire&signature=A4266FFEA1ADCBE97BCA72094E54BF6636CAFACD.882F245693D250AC328D95E6CE49997821E269A6&ratebypass=yes&ipbits=0", "format_id": "43", "height": 360, "player_url": null}, 
{"width": 640, "ext": "mp4", "format": "18 - 640x360", "url": "https://r14---sn-4g57kn6r.googlevideo.com/videoplayback?itag=18&mt=1395407808&upn=MxVzxKsbd3U&id=o-ALe2D0epTKGnwRqasgNf3CLxJbn33_ML0va0EAMhxV3S&mv=u&source=youtube&sver=3&expire=1395432694&key=yt5&ip=217.159.229.217&requiressl=yes&fexp=933513%2C912307%2C936906%2C929202%2C916612%2C906010%2C933611%2C937417%2C913434%2C936910%2C936913%2C934022&mws=yes&ms=au&sparams=id%2Cip%2Cipbits%2Citag%2Cratebypass%2Crequiressl%2Csource%2Cupn%2Cexpire&signature=22B214A690C3AD190EF49D474602577939520490.6B1F165E5B3E24018758D1D5A56C76B4B482A9A8&ratebypass=yes&ipbits=0", "format_id": "18", "height": 360, "player_url": null}, 
{"width": 1280, "ext": "mp4", "format": "22 - 1280x720", "url": "https://r14---sn-4g57kn6r.googlevideo.com/videoplayback?itag=22&mt=1395407808&upn=MxVzxKsbd3U&id=o-ALe2D0epTKGnwRqasgNf3CLxJbn33_ML0va0EAMhxV3S&mv=u&source=youtube&sver=3&expire=1395432694&key=yt5&ip=217.159.229.217&requiressl=yes&fexp=933513%2C912307%2C936906%2C929202%2C916612%2C906010%2C933611%2C937417%2C913434%2C936910%2C936913%2C934022&mws=yes&ms=au&sparams=id%2Cip%2Cipbits%2Citag%2Cratebypass%2Crequiressl%2Csource%2Cupn%2Cexpire&signature=9058F3204B221AB0EAEC84231EFA385534216639.9E0959AC2931BD16BB898DF5DA40D32609390080&ratebypass=yes&ipbits=0", "format_id": "22", "height": 720, "player_url": null}], "fulltitle": "Build an Editing/Gaming/Capture PC: Meet The Ocelot", "age_limit": 0, "thumbnail": "https://i1.ytimg.com/vi/0xJy2QVJTx8/maxresdefault.jpg", "webpage_url_basename": "watch"}
